o2_speechless/__init__.py
o2_speechless/globals.py
o2_speechless/audio/__init__.py
o2_speechless/audio/conversion.py
o2_speechless/audio/download.py
o2_speechless/audio/onnx.py
o2_speechless/audio/preprocessing.py
o2_speechless/audio/quality.py
o2_speechless/audio/speaker_diarization.py
o2_speechless/audio/provider/elevenlabs/transcribe.py
o2_speechless/audio/provider/openai/transcribe.py
o2_speechless/llm/__init__.py
o2_speechless/llm/language.py
o2_speechless/llm/sentiment_analysis.py
o2_speechless/llm/text_processor.py
o2_speechless/llm/provider/__init__.py
o2_speechless/llm/provider/openai/__init__.py
o2_speechless/llm/provider/openai/client.py
o2_speechless/llm/provider/openai/constants/__init__.py
o2_speechless/llm/provider/openai/constants/prompts/__init__.py
o2_speechless/llm/provider/openai/constants/prompts/sentiment_score.py
o2_speechless/llm/provider/openai/constants/prompts/summarization.py
o2_speechless/llm/provider/openai/constants/prompts/summarization_sk.py
o2_speechless/llm/provider/openai/constants/prompts/tags.py
o2_speechless/util/__init__.py
o2_speechless/util/logger.py
o2_speechless-0.0.9.dist-info/METADATA
o2_speechless-0.0.9.dist-info/WHEEL
o2_speechless-0.0.9.dist-info/top_level.txt
o2_speechless-0.0.9.dist-info/RECORD
