Metadata-Version: 2.4
Name: o2-speechless
Version: 0.0.9
Summary: Speechless repo for sales call analysis
Author-email: Michal Pleva <michal@miya.consulting>, Niek Mereu <niek@miya.consulting>, Jan Mikulaš <jan@miya.consulting>
License: MIT
Requires-Python: <3.11,>=3.10
Requires-Dist: twine<6.0.0,>=5.1.1
Requires-Dist: pytubefix<8.0.0,>=7.4.0
Requires-Dist: python-dotenv<2.0.0,>=1.0.1
Requires-Dist: openai<2.0.0,>=1.51.2
Requires-Dist: pvfalcon<2.0.0,>=1.0.2
Requires-Dist: pydub<0.26.0,>=0.25.1
Requires-Dist: streamlit<2.0,>=1.44
Requires-Dist: numba<0.62,>=0.61
Requires-Dist: pyannote-audio<4.0,>=3.3.2
Requires-Dist: onnx<2.0,>=1.17.0
Requires-Dist: onnxruntime<2.0,>=1.20.0
Requires-Dist: streamlit-audiorec<0.2.0,>=0.1.3
Requires-Dist: noisereduce<4.0,>=3.0.3
Requires-Dist: silero-vad<6.0,>=5.1.2
Requires-Dist: tiktoken<1.0,>=0.8.0
Requires-Dist: librosa<0.12,>=0.11.0
Requires-Dist: streamlit-advanced-audio<0.2.0,>=0.1.1
Requires-Dist: websockets<16.0,>=15.0.1
Requires-Dist: streamlit-webrtc<0.61,>=0.60.2
Requires-Dist: thefuzz>=0.22.1
Requires-Dist: elevenlabs>=2.1.0
